exhausterr/__init__.py
exhausterr/_builtin.py
exhausterr/_errors.py
exhausterr/_iterators.py
exhausterr/_results.py
exhausterr/py.typed
exhausterr/type_utils.py
exhausterr-0.4.1.dist-info/METADATA
exhausterr-0.4.1.dist-info/WHEEL
exhausterr-0.4.1.dist-info/licenses/LICENSE.txt
exhausterr-0.4.1.dist-info/RECORD
