Metadata-Version: 2.4
Name: exhausterr
Version: 0.4.1
Summary: Exhaustive error handling for Python
Project-URL: Documentation, https://github.com/Hedwyn/exhausterr#readme
Project-URL: Issues, https://github.com/Hedwyn/exhausterr/issues
Project-URL: Source, https://github.com/Hedwyn/exhausterr
Author-email: Hedwyn <bpestourie@gmail.com>
License-Expression: MIT
License-File: LICENSE.txt
Classifier: Development Status :: 4 - Beta
Classifier: Programming Language :: Python
Classifier: Programming Language :: Python :: 3.11
Classifier: Programming Language :: Python :: 3.12
Classifier: Programming Language :: Python :: Implementation :: CPython
Classifier: Programming Language :: Python :: Implementation :: PyPy
Classifier: Programming Language :: Rust
Requires-Python: >=3.11
Provides-Extra: test
Requires-Dist: pytest; extra == 'test'
